[
  {
    "nombre": "Senna",
    "win": "49.08%"
  },
  {
    "nombre": "Thresh",
    "win": "51.12%"
  },
  {
    "nombre": "Lux",
    "win": "53.35%"
  },
  {
    "nombre": "Karma",
    "win": "50.86%"
  },
  {
    "nombre": "Nautilus",
    "win": "51.71%"
  },
  {
    "nombre": "Blitzcrank",
    "win": "49.62%"
  },
  {
    "nombre": "Nami",
    "win": "48.25%"
  },
  {
    "nombre": "Leona",
    "win": "50.75%"
  },
  {
    "nombre": "Lulu",
    "win": "50.85%"
  },
  {
    "nombre": "Pyke",
    "win": "49.22%"
  },
  {
    "nombre": "Seraphine",
    "win": "52.46%"
  },
  {
    "nombre": "Yuumi",
    "win": "48.60%"
  },
  {
    "nombre": "Milio",
    "win": "47.74%"
  },
  {
    "nombre": "Rell",
    "win": "48.90%"
  },
  {
    "nombre": "Bardo",
    "win": "49.74%"
  },
  {
    "nombre": "Soraka",
    "win": "46.96%"
  },
  {
    "nombre": "Rakan",
    "win": "53.48%"
  },
  {
    "nombre": "Morgana",
    "win": "56.04%"
  },
  {
    "nombre": "Zyra",
    "win": "50.00%"
  },
  {
    "nombre": "Braum",
    "win": "52.44%"
  },
  {
    "nombre": "Alistar",
    "win": "52.83%"
  },
  {
    "nombre": "Janna",
    "win": "47.45%"
  },
  {
    "nombre": "Vel'Koz",
    "win": "51.15%"
  },
  {
    "nombre": "Poppy",
    "win": "46.40%"
  },
  {
    "nombre": "Zilean",
    "win": "51.50%"
  },
  {
    "nombre": "Brand",
    "win": "55.43%"
  },
  {
    "nombre": "Shaco",
    "win": "47.55%"
  },
  {
    "nombre": "Sona",
    "win": "49.91%"
  },
  {
    "nombre": "Maokai",
    "win": "48.23%"
  },
  {
    "nombre": "Neeko",
    "win": "54.10%"
  },
  {
    "nombre": "Swain",
    "win": "54.12%"
  },
  {
    "nombre": "Pantheon",
    "win": "50.21%"
  },
  {
    "nombre": "Hwei",
    "win": "58.92%"
  },
  {
    "nombre": "Tahm Kench",
    "win": "45.27%"
  },
  {
    "nombre": "LeBlanc",
    "win": "49.67%"
  },
  {
    "nombre": "Camille",
    "win": "46.46%"
  },
  {
    "nombre": "Ashe",
    "win": "60.34%"
  },
  {
    "nombre": "Taric",
    "win": "50.78%"
  },
  {
    "nombre": "Zac",
    "win": "47.64%"
  },
  {
    "nombre": "Renata Glasc",
    "win": "55.65%"
  },
  {
    "nombre": "Amumu",
    "win": "49.09%"
  },
  {
    "nombre": "Zoe",
    "win": "43.00%"
  },
  {
    "nombre": "Fiddlesticks",
    "win": "57.50%"
  },
  {
    "nombre": "Shen",
    "win": "56.64%"
  }
]